asyncupbit/__init__.py
asyncupbit/client.py
asyncupbit/errors.py
asyncupbit/py.typed
asyncupbit/types.py
asyncupbit-0.1.1.dist-info/LICENSE
asyncupbit-0.1.1.dist-info/METADATA
asyncupbit-0.1.1.dist-info/WHEEL
asyncupbit-0.1.1.dist-info/RECORD
